completion_utils
