Metadata-Version: 2.1
Name: completion-utils
Version: 0.0.2
Summary: A set of functions intended to make writing shell completion functions lot easier by letting you write them via python.
Home-page: https://github.com/CarvellScott/completion_utils
Author: Carvell Scott
Author-email: carvell.scott@gmail.com
License: UNKNOWN
Keywords: bash completion,complete,autocomplete,auto-complete
Platform: UNKNOWN
Classifier: Development Status :: 3 - Alpha
Classifier: Intended Audience :: Developers
Classifier: Topic :: Software Development
Classifier: License :: OSI Approved :: GNU General Public License v3 (GPLv3)
Classifier: Programming Language :: Python :: 3
Classifier: Programming Language :: Python :: 3.5
Classifier: Programming Language :: Python :: 3.6
